gz/__init__.py
gz/common5.cpython-311-x86_64-linux-gnu.so
gz/math7.cpython-311-x86_64-linux-gnu.so
gz/sim8.cpython-311-x86_64-linux-gnu.so
gz/msgs10/__init__.py
gz/msgs10/actor_pb2.py
gz/msgs10/actuators_pb2.py
gz/msgs10/air_pressure_sensor_pb2.py
gz/msgs10/air_speed_pb2.py
gz/msgs10/air_speed_sensor_pb2.py
gz/msgs10/altimeter_pb2.py
gz/msgs10/altimeter_sensor_pb2.py
gz/msgs10/annotated_axis_aligned_2d_box_pb2.py
gz/msgs10/annotated_axis_aligned_2d_box_v_pb2.py
gz/msgs10/annotated_oriented_3d_box_pb2.py
gz/msgs10/annotated_oriented_3d_box_v_pb2.py
gz/msgs10/any_pb2.py
gz/msgs10/atmosphere_pb2.py
gz/msgs10/axis_aligned_2d_box_pb2.py
gz/msgs10/axis_aligned_box_pb2.py
gz/msgs10/axis_pb2.py
gz/msgs10/battery_pb2.py
gz/msgs10/battery_state_pb2.py
gz/msgs10/boolean_pb2.py
gz/msgs10/boxgeom_pb2.py
gz/msgs10/bytes_pb2.py
gz/msgs10/camera_cmd_pb2.py
gz/msgs10/camera_info_pb2.py
gz/msgs10/camera_lens_pb2.py
gz/msgs10/camerasensor_pb2.py
gz/msgs10/cameratrack_pb2.py
gz/msgs10/capsulegeom_pb2.py
gz/msgs10/cessna_pb2.py
gz/msgs10/clock_pb2.py
gz/msgs10/cmd_vel2d_pb2.py
gz/msgs10/collision_pb2.py
gz/msgs10/color_pb2.py
gz/msgs10/conegeom_pb2.py
gz/msgs10/contact_pb2.py
gz/msgs10/contacts_pb2.py
gz/msgs10/contactsensor_pb2.py
gz/msgs10/cylindergeom_pb2.py
gz/msgs10/data_load_options_pb2.py
gz/msgs10/dataframe_pb2.py
gz/msgs10/density_pb2.py
gz/msgs10/diagnostics_pb2.py
gz/msgs10/discovery_pb2.py
gz/msgs10/distortion_pb2.py
gz/msgs10/double_pb2.py
gz/msgs10/double_v_pb2.py
gz/msgs10/duration_pb2.py
gz/msgs10/dvl_beam_state_pb2.py
gz/msgs10/dvl_kinematic_estimate_pb2.py
gz/msgs10/dvl_range_estimate_pb2.py
gz/msgs10/dvl_tracking_target_pb2.py
gz/msgs10/dvl_velocity_tracking_pb2.py
gz/msgs10/ellipsoidgeom_pb2.py
gz/msgs10/empty_pb2.py
gz/msgs10/entity_factory_pb2.py
gz/msgs10/entity_factory_v_pb2.py
gz/msgs10/entity_pb2.py
gz/msgs10/entity_plugin_v_pb2.py
gz/msgs10/entity_wrench_map_pb2.py
gz/msgs10/entity_wrench_pb2.py
gz/msgs10/float_pb2.py
gz/msgs10/float_v_pb2.py
gazebo_py_bindings-1.0.0.dist-info/LICENSE
gazebo_py_bindings-1.0.0.dist-info/METADATA
gazebo_py_bindings-1.0.0.dist-info/WHEEL
gazebo_py_bindings-1.0.0.dist-info/top_level.txt
gazebo_py_bindings-1.0.0.dist-info/RECORD
